HPDMSTD205/__init__.py
HPDMSTD205/readHPDM.py
HPDMSTD205-0.1.0.dist-info/METADATA
HPDMSTD205-0.1.0.dist-info/WHEEL
HPDMSTD205-0.1.0.dist-info/top_level.txt
HPDMSTD205-0.1.0.dist-info/RECORD
