Metadata-Version: 2.1
Name: HPDMSTD205
Version: 0.1.0
Summary: Generating HVAC&R performance table - ASHRAE STD 205
Home-page: UNKNOWN
Author: Hanlong Wan, Bo Shen (ORNL)
Author-email: <wanh@ornl.gov>
License: UNKNOWN
Keywords: python,ASHRAE,performance table,HPDM,standard 205
Platform: UNKNOWN
Classifier: Development Status :: 1 - Planning
Classifier: Intended Audience :: Developers
Classifier: Programming Language :: Python :: 3
Classifier: Operating System :: Unix
Classifier: Operating System :: MacOS :: MacOS X
Classifier: Operating System :: Microsoft :: Windows
Requires-Dist: pandas
Requires-Dist: json
Requires-Dist: pint
